mercado_bitcoin_dados/__init__.py
mercado_bitcoin_dados/crypto_asset.py
mercado_bitcoin_dados/mercado_bitcoin_data.py
mercado_bitcoin_dados/model.py
mercado_bitcoin_dados-0.1.0.dist-info/WHEEL
mercado_bitcoin_dados-0.1.0.dist-info/METADATA
mercado_bitcoin_dados-0.1.0.dist-info/RECORD
