Metadata-Version: 2.1
Name: mercado-bitcoin-dados
Version: 0.1.0
Summary: 
Author: Nicolas Rodriguez Celys
Author-email: n.rodri.eng.soft@gmail.com
Requires-Python: >=3.7.1,<4.0.0
Classifier: Programming Language :: Python :: 3
Classifier: Programming Language :: Python :: 3.8
Classifier: Programming Language :: Python :: 3.9
Requires-Dist: pandas (>=1.2.2,<2.0.0)
Requires-Dist: requests (>=2.25.1,<3.0.0)
